bluebelt/__init__.py
bluebelt/version.py
bluebelt/analysis/__init__.py
bluebelt/analysis/datetime.py
bluebelt/analysis/distribution.py
bluebelt/analysis/forecast.py
bluebelt/analysis/pattern.py
bluebelt/analysis/performance.py
bluebelt/analysis/planning.py
bluebelt/core/__init__.py
bluebelt/core/dataframe.py
bluebelt/core/filter.py
bluebelt/core/forecast.py
bluebelt/core/series.py
bluebelt/core/timeline.py
bluebelt/core/workforce.py
bluebelt/core/workload.py
bluebelt/create/__init__.py
bluebelt/create/create.py
bluebelt/data/__init__.py
bluebelt/data/projection.py
bluebelt/data/resolution.py
bluebelt/data/shape.py
bluebelt/data/timeline.py
bluebelt/graph/__init__.py
bluebelt/graph/_default_plot_params.py
bluebelt/graph/graph.py
bluebelt/helpers/__init__.py
bluebelt/helpers/boxplot.py
bluebelt/helpers/check.py
bluebelt/helpers/ci.py
bluebelt/helpers/colors.py
bluebelt/helpers/constants.py
bluebelt/helpers/convert.py
bluebelt/helpers/date.py
bluebelt/helpers/holidays.py
bluebelt/helpers/io.py
bluebelt/helpers/language.py
bluebelt/helpers/matplotlib2plotly.py
bluebelt/helpers/text.py
bluebelt/helpers/ticks.py
bluebelt/helpers/decorators/__init__.py
bluebelt/helpers/decorators/docstring.py
bluebelt/helpers/decorators/pattern.py
bluebelt/helpers/decorators/performance.py
bluebelt/statistics/__init__.py
bluebelt/statistics/basic.py
bluebelt/statistics/hypothesis_testing.py
bluebelt/statistics/std.py
bluebelt/styles/__init__.py
bluebelt/styles/fat.yaml
bluebelt/styles/paper.yaml
bluebelt/styles/rc.py
bluebelt/styles/rc.yaml
bluebelt-0.2.20.dist-info/LICENSE
bluebelt-0.2.20.dist-info/METADATA
bluebelt-0.2.20.dist-info/WHEEL
bluebelt-0.2.20.dist-info/top_level.txt
bluebelt-0.2.20.dist-info/RECORD
