Metadata-Version: 2.1
Name: bluebelt
Version: 0.2.20
Summary: Tools for HR analytics.
Home-page: https://www.maanrijp.nl
Author: Arvid Hahné
Author-email: arvid@maanrijp.nl
License: GNU GPLv3
Classifier: Development Status :: 3 - Alpha
Classifier: Intended Audience :: Science/Research
Classifier: Programming Language :: Python :: 3.7
License-File: LICENSE
